{
  "nav": [ 
    {"link":"/", "name":"Inicio"},
    {"link":"/docs/", "name":"Documentación"},
    {"link":"/descargar.html", "name":"Descargar"}
  ],
  "navejemplos": [ 
    {"link":"/examples/article.html", "name":"Textos"},
    {"link":"/examples/gallery.html", "name":"Multimedia"},
    {"link":"/examples/listas.html", "name":"Listas"},
    {"link":"/examples/contacto.html", "name":"Formularios"},
    {"link":"/examples/tools.html", "name":"Herramientas"}
  ],
  "htmlbase": [ 
    {"link":"/docs/#titulos", "anchor":"#titulos", "name":"titulos"},
    {"link":"/docs/#parrafos", "anchor":"#parrafos", "name":"parrafos"},
    {"link":"/docs/#listas", "anchor":"#listas", "name":"listas"},
    {"link":"/docs/#tablas", "anchor":"#tablas", "name":"tablas"}
  ],
  "elementos": [ 
    {"link":"/docs/elm.html#formularios", "anchor":"#formularios", "name":"formularios"},
    {"link":"/docs/elm.html#galeria", "anchor":"#galeria", "name":"galeria"},
    {"link":"/docs/elm.html#navegacion", "anchor":"#navegacion", "name":"navegación"},
    {"link":"/docs/elm.html#pasadores", "anchor":"#pasadores", "name":"pasadores"},
    {"link":"/docs/elm.html#carrusel", "anchor":"#carrusel", "name":"carrusel"}
  ],
  "documentos": [ 
    {"link":"/docs/docs.html#caracter-sticas", "anchor":"#caracter-sticas", "name":"características"},
    {"link":"/docs/docs.html#recursos-javascript", "anchor":"#recursos-javascript", "name":"recursos javascript"},
    {"link":"/docs/docs.html#recursos-less", "anchor":"#recursos-less", "name":"recursos less"},
    {"link":"/docs/docs.html#instalaci-n", "anchor":"#instalaci-n", "name":"instalación"},
    {"link":"/docs/docs.html#como-funciona", "anchor":"#como-funciona", "name":"como funciona"},
    {"link":"/docs/docs.html#instruccion-para-trabajar-con-less-en-snippets", "anchor":"#instruccion-para-trabajar-con-less-en-snippets", "name":"como usar less"},
    {"link":"/docs/docs.html#jade", "anchor":"#jade", "name":"como usar jade"}
  ],
  "user": {
    "name": "User Name",
    "provider": "github",
    "image": "/media/upload/user.png"
  },
  "page": {
    "title": "snippets",
    "decription": "framework frontend: nodejs + jade + less"
  }
}
